psychopy_session_webserver/__init__.py
psychopy_session_webserver/__main__.py
psychopy_session_webserver/async_task_runner.py
psychopy_session_webserver/dependency_checker.py
psychopy_session_webserver/file_event_handler.py
psychopy_session_webserver/main.py
psychopy_session_webserver/options.py
psychopy_session_webserver/participants_registry.py
psychopy_session_webserver/server.py
psychopy_session_webserver/session.py
psychopy_session_webserver/types.py
psychopy_session_webserver/update_broadcaster.py
psychopy_session_webserver/utils.py
psychopy_session_webserver-0.0.1a4.dist-info/METADATA
psychopy_session_webserver-0.0.1a4.dist-info/WHEEL
psychopy_session_webserver-0.0.1a4.dist-info/top_level.txt
psychopy_session_webserver-0.0.1a4.dist-info/RECORD
