Metadata-Version: 2.1
Name: psychopy_session_webserver
Version: 0.0.1a4
Summary: A small example package
Author-email: Alexandre Tuleu <alexandre.tuleu.2005@polytechnique.org>
License: GNU General Public License v3 (GPLv3)
Project-URL: Homepage, https://github.com/iNkawuVervetProject/VerTIGo/tree/main/psychopy-session-webserver
Project-URL: Issues, https://github.com/iNkawuVervetProject/VerTIGo/issues
Classifier: Programming Language :: Python :: 3
Classifier: License :: OSI Approved :: GNU General Public License v3 (GPLv3)
Classifier: License :: OSI Approved :: MIT License
Requires-Python: >=3.8
Requires-Dist: hypercorn
Requires-Dist: fastapi
Requires-Dist: psychopy ==2024.1.4
Requires-Dist: watchdog
Requires-Dist: structlog
Requires-Dist: numpy <2
Requires-Dist: netifaces
Requires-Dist: PyXDG
Provides-Extra: dev
Requires-Dist: black >=22.10 ; extra == 'dev'
Requires-Dist: pytest ; extra == 'dev'
